README.md
setup.py
PyleWM.egg-info/PKG-INFO
PyleWM.egg-info/SOURCES.txt
PyleWM.egg-info/dependency_links.txt
PyleWM.egg-info/entry_points.txt
PyleWM.egg-info/requires.txt
PyleWM.egg-info/top_level.txt
pylewm/PyleWM.png
pylewm/__init__.py
pylewm/__main__.py
pylewm/alt_mode.py
pylewm/commands.py
pylewm/config.py
pylewm/dropdown.py
pylewm/execution.py
pylewm/filters.py
pylewm/focus.py
pylewm/hotkeys.py
pylewm/layout.py
pylewm/monitors.py
pylewm/pylewm_default_config.py
pylewm/pylewm_example_config.py
pylewm/rects.py
pylewm/run.py
pylewm/selector.py
pylewm/sendkeys.py
pylewm/space.py
pylewm/spaces.py
pylewm/window.py
pylewm/window_classification.py
pylewm/windows.py
pylewm/wsltty.py
pylewm/yank.py
pylewm/data/COPYING
pylewm/data/TerminusTTF-4.47.0.ttf
pylewm/data/TerminusTTF-Bold Italic-4.47.0.ttf
pylewm/data/TerminusTTF-Bold-4.47.0.ttf
pylewm/data/TerminusTTF-Italic-4.47.0.ttf
pylewm/layouts/__init__.py
pylewm/layouts/autogrid.py
pylewm/layouts/columns.py
pylewm/layouts/sidebar.py
pylewm/modes/__init__.py
pylewm/modes/goto_window.py
pylewm/modes/hint_helpers.py
pylewm/modes/hint_mouse.py
pylewm/modes/hint_window.py
pylewm/modes/keynav.py
pylewm/modes/list_mode.py
pylewm/modes/overlay_mode.py
pylewm/modes/select_application.py